{
  "image_file": "0d1a16d46aae_PC000011_MOV-0014_jpg_rf_e7aeafd0705626f1498ec375c767ebb1.png",
  "image_sha256": "0d1a16d46aae470633d860ba97223731ffb2c6b92b819c0425933869d9b62b25",
  "image_width": 640,
  "image_height": 360,
  "detector_config": {
    "library": "pupil-apriltags",
    "library_version": "1.0.4.post11",
    "family": "tag36h11",
    "nthreads": 4,
    "quad_decimate": 1.0,
    "quad_sigma": 0.0,
    "refine_edges": true,
    "decode_sharpening": 0.25
  },
  "detected_at": "2026-03-24T14:13:55.793627+00:00",
  "num_detections": 1,
  "detections": [
    {
      "tag_id": 17,
      "tag_family": "tag36h11",
      "hamming": 0,
      "decision_margin": 90.38961029052734,
      "center": [
        245.62176495410583,
        152.6023487148428
      ],
      "corners": [
        [
          174.0830841064453,
          203.76632690429693
        ],
        [
          289.736572265625,
          243.54464721679685
        ],
        [
          326.8905029296875,
          94.4794998168945
        ],
        [
          205.42514038085935,
          69.7373504638672
        ]
      ],
      "homography": [
        [
          45.5519230967011,
          -14.901966407682176,
          245.62176495410583
        ],
        [
          7.742627106344022,
          71.88148581399386,
          152.6023487148428
        ],
        [
          -0.05507401332234684,
          0.008601279427517927,
          1.0
        ]
      ]
    }
  ]
}
