{
  "image_file": "18770d73a8f2_FRC_team_1690_Orbit_2024_robot_reveal_-__DOPPLER__frame_0004.png",
  "image_sha256": "18770d73a8f2527865dd3359921d411e023966f5fd6545f41d4b4a3f019fb127",
  "image_width": 1920,
  "image_height": 1080,
  "detector_config": {
    "library": "pupil-apriltags",
    "library_version": "1.0.4.post11",
    "family": "tag36h11",
    "nthreads": 4,
    "quad_decimate": 1.0,
    "quad_sigma": 0.0,
    "refine_edges": true,
    "decode_sharpening": 0.25
  },
  "detected_at": "2026-04-01T00:30:26.303631+00:00",
  "num_detections": 1,
  "detections": [
    {
      "tag_id": 12,
      "tag_family": "tag36h11",
      "hamming": 0,
      "decision_margin": 66.398193359375,
      "center": [
        1521.9210884374552,
        248.48879566283134
      ],
      "corners": [
        [
          1492.2219238281252,
          279.3282165527344
        ],
        [
          1550.5577392578125,
          281.79547119140625
        ],
        [
          1551.9184570312498,
          217.3397216796875
        ],
        [
          1492.6495361328123,
          214.4436798095703
        ]
      ],
      "homography": [
        [
          33.94093921887861,
          11.695918083453765,
          1521.9210884374552
        ],
        [
          2.0807516797408385,
          34.31550966344062,
          248.48879566283134
        ],
        [
          0.0029842991415006577,
          0.007979630837728778,
          1.0
        ]
      ]
    }
  ]
}
