{
  "image_file": "1ec91cc3f1a5_Team_2503___2026_Robot_Reveal_frame_001080.png",
  "image_sha256": "1ec91cc3f1a57e3c4d53dc1e671b0dbd7dd2e17e34659ef807b7eb3d4d901a8d",
  "image_width": 1800,
  "image_height": 1080,
  "detector_config": {
    "library": "pupil-apriltags",
    "library_version": "1.0.4.post11",
    "family": "tag36h11",
    "nthreads": 4,
    "quad_decimate": 1.0,
    "quad_sigma": 0.0,
    "refine_edges": true,
    "decode_sharpening": 0.25
  },
  "detected_at": "2026-04-01T04:40:55.359704+00:00",
  "num_detections": 5,
  "detections": [
    {
      "tag_id": 1,
      "tag_family": "tag36h11",
      "hamming": 0,
      "decision_margin": 68.87679290771484,
      "center": [
        300.96142980805547,
        482.64510565337935
      ],
      "corners": [
        [
          285.127716064453,
          495.08343505859375
        ],
        [
          315.6510009765625,
          495.2294311523438
        ],
        [
          316.47167968750006,
          470.4608764648438
        ],
        [
          286.03344726562494,
          469.85653686523426
        ]
      ],
      "homography": [
        [
          18.003317252256636,
          -0.7728613922716909,
          300.96142980805547
        ],
        [
          4.620797859187006,
          11.949958465250234,
          482.64510565337935
        ],
        [
          0.009184739137917843,
          -0.001135074528533099,
          1.0
        ]
      ]
    },
    {
      "tag_id": 3,
      "tag_family": "tag36h11",
      "hamming": 0,
      "decision_margin": 79.38043975830078,
      "center": [
        818.7934436591758,
        454.9065253498094
      ],
      "corners": [
        [
          805.1930541992188,
          467.1011657714844
        ],
        [
          831.25390625,
          467.9819641113281
        ],
        [
          832.1953735351564,
          442.8898315429688
        ],
        [
          806.3218994140625,
          441.81945800781256
        ]
      ],
      "homography": [
        [
          16.174135025510736,
          -3.3442008363489304,
          818.7934436591758
        ],
        [
          2.2609345502485767,
          11.022510505103241,
          454.9065253498094
        ],
        [
          0.003897099316567489,
          -0.0034526242944839416,
          1.0
        ]
      ]
    },
    {
      "tag_id": 4,
      "tag_family": "tag36h11",
      "hamming": 0,
      "decision_margin": 79.26583099365234,
      "center": [
        874.3267162011133,
        457.22975115556875
      ],
      "corners": [
        [
          861.4160766601562,
          469.1300354003906
        ],
        [
          886.2713012695311,
          469.83560180664057
        ],
        [
          887.0830688476564,
          445.47167968750006
        ],
        [
          862.1702880859375,
          444.4003295898438
        ]
      ],
      "homography": [
        [
          18.911715052399927,
          0.8230160685832312,
          874.3267162011133
        ],
        [
          3.827657432320107,
          12.907953432724298,
          457.22975115556875
        ],
        [
          0.007400449926432403,
          0.0013893484585613632,
          1.0
        ]
      ]
    },
    {
      "tag_id": 14,
      "tag_family": "tag36h11",
      "hamming": 1,
      "decision_margin": 40.11737823486328,
      "center": [
        511.55837782154157,
        531.3541713617421
      ],
      "corners": [
        [
          503.9120788574219,
          537.8004760742188
        ],
        [
          519.0618896484374,
          538.2169189453123
        ],
        [
          519.664794921875,
          524.5199584960938
        ],
        [
          504.0577697753906,
          524.494079589844
        ]
      ],
      "homography": [
        [
          0.1653409785534441,
          7.2377156444800335,
          511.55837782154157
        ],
        [
          -7.698116466069111,
          14.456701730283724,
          531.3541713617421
        ],
        [
          -0.01470117256453765,
          0.014507640336751755,
          1.0
        ]
      ]
    },
    {
      "tag_id": 15,
      "tag_family": "tag36h11",
      "hamming": 1,
      "decision_margin": 31.887575149536133,
      "center": [
        742.152198417313,
        534.9384008964312
      ],
      "corners": [
        [
          735.4085693359376,
          541.4110107421875
        ],
        [
          748.4443969726564,
          541.5322265625001
        ],
        [
          748.6926879882811,
          528.6607666015625
        ],
        [
          735.7437744140626,
          528.2227783203125
        ]
      ],
      "homography": [
        [
          15.565381404145,
          -2.4240473146626282,
          742.152198417313
        ],
        [
          6.678035817392355,
          4.871438699590727,
          534.9384008964312
        ],
        [
          0.01222153436701023,
          -0.0030703728888258433,
          1.0
        ]
      ]
    }
  ]
}
