{
  "image_file": "359d680ed779_FRC_GAME_POV___Close_Match_at_SCR__frame_007140.png",
  "image_sha256": "359d680ed779cb17545b8462d6357e0d204c7fcc7f8552d493e2ccaa855944d5",
  "image_width": 1920,
  "image_height": 1080,
  "detector_config": {
    "library": "pupil-apriltags",
    "library_version": "1.0.4.post11",
    "family": "tag36h11",
    "nthreads": 4,
    "quad_decimate": 1.0,
    "quad_sigma": 0.0,
    "refine_edges": true,
    "decode_sharpening": 0.25
  },
  "detected_at": "2026-04-01T16:19:59.632969+00:00",
  "num_detections": 4,
  "detections": [
    {
      "tag_id": 7,
      "tag_family": "tag36h11",
      "hamming": 0,
      "decision_margin": 27.360034942626953,
      "center": [
        1382.9630209469644,
        665.3491876523207
      ],
      "corners": [
        [
          1361.7277832031252,
          691.5001220703125
        ],
        [
          1410.0025634765627,
          686.0372314453127
        ],
        [
          1404.516357421875,
          638.8065185546875
        ],
        [
          1357.137939453125,
          645.5903320312497
        ]
      ],
      "homography": [
        [
          2.8796916926391996,
          -8.23219214632445,
          1382.9630209469644
        ],
        [
          -13.181999528500798,
          18.109683684757556,
          665.3491876523207
        ],
        [
          -0.015203618160581599,
          -0.007769420202849592,
          1.0
        ]
      ]
    },
    {
      "tag_id": 8,
      "tag_family": "tag36h11",
      "hamming": 0,
      "decision_margin": 50.90191650390625,
      "center": [
        1222.5808034323918,
        686.7981168448554
      ],
      "corners": [
        [
          1202.599731445313,
          711.7635498046875
        ],
        [
          1247.9942626953125,
          706.9874267578125
        ],
        [
          1243.523315429687,
          660.6314086914064
        ],
        [
          1198.2471923828125,
          667.4666748046876
        ]
      ],
      "homography": [
        [
          -4.974361278967081,
          3.29789612290142,
          1222.5808034323918
        ],
        [
          -18.422192299354382,
          23.26508874829494,
          686.7981168448554
        ],
        [
          -0.02260015686748922,
          0.00089338686962098,
          1.0
        ]
      ]
    },
    {
      "tag_id": 9,
      "tag_family": "tag36h11",
      "hamming": 0,
      "decision_margin": 63.01164627075195,
      "center": [
        371.7078510125144,
        750.4356550520462
      ],
      "corners": [
        [
          353.58441162109375,
          762.676513671875
        ],
        [
          383.75186157226557,
          769.195068359375
        ],
        [
          389.49029541015625,
          738.4251098632812
        ],
        [
          359.5029602050782,
          731.4256591796873
        ]
      ],
      "homography": [
        [
          18.035712949906838,
          -3.4456862385582645,
          371.7078510125144
        ],
        [
          9.432439745556733,
          14.430227158375944,
          750.4356550520462
        ],
        [
          0.008065724449977484,
          -0.001431186857987308,
          1.0
        ]
      ]
    },
    {
      "tag_id": 10,
      "tag_family": "tag36h11",
      "hamming": 0,
      "decision_margin": 67.65478515625,
      "center": [
        129.6231559542908,
        690.9093792943903
      ],
      "corners": [
        [
          109.75148010253905,
          703.2250366210938
        ],
        [
          140.5984649658203,
          711.284912109375
        ],
        [
          148.7968444824219,
          679.0263061523436
        ],
        [
          118.57550048828128,
          670.3995361328125
        ]
      ],
      "homography": [
        [
          16.63540479650888,
          -5.1982233401508875,
          129.6231559542908
        ],
        [
          11.483776573957355,
          11.22835999701738,
          690.9093792943903
        ],
        [
          0.010580681731883826,
          -0.007295635590442854,
          1.0
        ]
      ]
    }
  ]
}
