{
  "image_file": "3b17d9a12f10_PC000001_MOV-0096_jpg_rf_cd29219975e248f1306ec0a6da710f46.png",
  "image_sha256": "3b17d9a12f10a792a74d0ca1c1288f976a22db59a40f0430071659eb1fe5cff5",
  "image_width": 640,
  "image_height": 360,
  "detector_config": {
    "library": "pupil-apriltags",
    "library_version": "1.0.4.post11",
    "family": "tag36h11",
    "nthreads": 4,
    "quad_decimate": 1.0,
    "quad_sigma": 0.0,
    "refine_edges": true,
    "decode_sharpening": 0.25
  },
  "detected_at": "2026-03-24T14:12:35.393713+00:00",
  "num_detections": 2,
  "detections": [
    {
      "tag_id": 15,
      "tag_family": "tag36h11",
      "hamming": 0,
      "decision_margin": 82.0843276977539,
      "center": [
        346.25024046587015,
        194.04898025102918
      ],
      "corners": [
        [
          339.39398193359375,
          202.63758850097656
        ],
        [
          352.38107299804693,
          204.32261657714852
        ],
        [
          353.2743530273438,
          185.25010681152347
        ],
        [
          340.0570068359375,
          183.67077636718744
        ]
      ],
      "homography": [
        [
          5.333530581784657,
          2.5815317244165503,
          346.25024046587015
        ],
        [
          0.13455410705458212,
          11.173639759008296,
          194.04898025102918
        ],
        [
          -0.003514776712003505,
          0.008578129742982969,
          1.0
        ]
      ]
    },
    {
      "tag_id": 16,
      "tag_family": "tag36h11",
      "hamming": 0,
      "decision_margin": 81.1313247680664,
      "center": [
        383.43004523907655,
        198.8425967996036
      ],
      "corners": [
        [
          375.5879516601563,
          207.73016357421872
        ],
        [
          390.7296142578125,
          209.95016479492185
        ],
        [
          391.96868896484364,
          189.1656188964844
        ],
        [
          376.03155517578125,
          187.58450317382815
        ]
      ],
      "homography": [
        [
          0.900205604041729,
          9.029056312711361,
          383.43004523907655
        ],
        [
          -2.6000993875856597,
          15.120676372118766,
          198.8425967996036
        ],
        [
          -0.01789615178035147,
          0.024626363164539103,
          1.0
        ]
      ]
    }
  ]
}
