{
  "image_file": "3f0e8722b432_PC000001_MOV-0047_jpg_rf_a8a5546d2a9087b9996520f5d7310d39.png",
  "image_sha256": "3f0e8722b43215f61437046a4d4b74633673e87ec8badd3a413aaf95b53f335d",
  "image_width": 640,
  "image_height": 360,
  "detector_config": {
    "library": "pupil-apriltags",
    "library_version": "1.0.4.post11",
    "family": "tag36h11",
    "nthreads": 4,
    "quad_decimate": 1.0,
    "quad_sigma": 0.0,
    "refine_edges": true,
    "decode_sharpening": 0.25
  },
  "detected_at": "2026-03-24T14:12:32.823205+00:00",
  "num_detections": 2,
  "detections": [
    {
      "tag_id": 13,
      "tag_family": "tag36h11",
      "hamming": 0,
      "decision_margin": 77.60958099365234,
      "center": [
        332.27225600257174,
        157.4422809091092
      ],
      "corners": [
        [
          318.5751037597656,
          167.73910522460938
        ],
        [
          342.2372131347657,
          173.19548034667972
        ],
        [
          345.90832519531244,
          147.19137573242188
        ],
        [
          322.20144653320307,
          141.52174377441406
        ]
      ],
      "homography": [
        [
          13.091071806695595,
          -1.3180177047721016,
          332.27225600257174
        ],
        [
          3.3731259330706376,
          13.295094464135758,
          157.4422809091092
        ],
        [
          0.0037589618459183518,
          0.0015242069631310753,
          1.0
        ]
      ]
    },
    {
      "tag_id": 14,
      "tag_family": "tag36h11",
      "hamming": 0,
      "decision_margin": 75.2765121459961,
      "center": [
        398.88812021356495,
        172.50507422841466
      ],
      "corners": [
        [
          383.44174194335943,
          183.0326385498047
        ],
        [
          409.66461181640625,
          189.1586456298828
        ],
        [
          414.7692565917968,
          161.68119812011716
        ],
        [
          388.1444091796875,
          155.90216064453122
        ]
      ],
      "homography": [
        [
          10.138754095666172,
          0.013717404465695714,
          398.88812021356495
        ],
        [
          1.6488874740817305,
          14.716548721001459,
          172.50507422841466
        ],
        [
          -0.007700541107457345,
          0.006177294811072072,
          1.0
        ]
      ]
    }
  ],
  "ingest_metadata": {
    "original_name": "PC000001_MOV-0047_jpg_rf_a8a5546d2a9087b9996520f5d7310d39.png",
    "source": "unknown",
    "dhash": "21e87eb49cec769a",
    "ingested_at": "2026-03-24T14:12:32.809212+00:00"
  }
}
