{
  "image_file": "65ffa670de12_FRC_TEAM_5484_s_Robot_Reveal_-_RAIJU_2024_frame_001829.png",
  "image_sha256": "65ffa670de12fe3fcb13f9fba12da91069d67583917f27b7c1ed8481915b1848",
  "image_width": 1920,
  "image_height": 1080,
  "detector_config": {
    "library": "pupil-apriltags",
    "library_version": "1.0.4.post11",
    "family": "tag36h11",
    "nthreads": 4,
    "quad_decimate": 1.0,
    "quad_sigma": 0.0,
    "refine_edges": true,
    "decode_sharpening": 0.25
  },
  "detected_at": "2026-04-01T00:38:37.655899+00:00",
  "num_detections": 2,
  "detections": [
    {
      "tag_id": 7,
      "tag_family": "tag36h11",
      "hamming": 0,
      "decision_margin": 61.36066436767578,
      "center": [
        1426.5673309990034,
        331.25560998359384
      ],
      "corners": [
        [
          1404.1671142578127,
          358.5235290527344
        ],
        [
          1449.2158203125,
          355.49078369140614
        ],
        [
          1449.1230468749998,
          303.7984008789062
        ],
        [
          1404.2781982421877,
          307.4049682617188
        ]
      ],
      "homography": [
        [
          14.30136511879573,
          -3.2419448988935056,
          1426.5673309990034
        ],
        [
          -3.5578173218333435,
          24.95020723126885,
          331.25560998359384
        ],
        [
          -0.005727854890705939,
          -0.002268931323714037,
          1.0
        ]
      ]
    },
    {
      "tag_id": 8,
      "tag_family": "tag36h11",
      "hamming": 0,
      "decision_margin": 69.06900787353516,
      "center": [
        1591.537751604874,
        296.78756582106485
      ],
      "corners": [
        [
          1567.3093261718748,
          326.68319702148443
        ],
        [
          1617.3050537109375,
          321.3633117675782
        ],
        [
          1616.2601318359377,
          266.28244018554676
        ],
        [
          1566.1121826171877,
          272.53775024414057
        ]
      ],
      "homography": [
        [
          11.692046486411527,
          3.2790903028198968,
          1591.537751604874
        ],
        [
          -5.380811767675031,
          27.8113276398455,
          296.78756582106485
        ],
        [
          -0.008383122727098109,
          0.001707718299182705,
          1.0
        ]
      ]
    }
  ],
  "ingest_metadata": {
    "original_name": "FRC_TEAM_5484_s_Robot_Reveal_-_RAIJU_2024_frame_001829.png",
    "source": "unknown",
    "dhash": "292f6c6c6bcd25d2",
    "ingested_at": "2026-04-01T00:38:37.645302+00:00"
  }
}
