{
  "image_file": "6dcc5ace3f2d_Hello_AprilTag_frame_079260.png",
  "image_sha256": "6dcc5ace3f2d2f2a8751b9f33a05e1f80fa145ab77e72c3627dcca3f7e5426bc",
  "image_width": 1920,
  "image_height": 1080,
  "detector_config": {
    "library": "pupil-apriltags",
    "library_version": "1.0.4.post11",
    "family": "tag36h11",
    "nthreads": 4,
    "quad_decimate": 1.0,
    "quad_sigma": 0.0,
    "refine_edges": true,
    "decode_sharpening": 0.25
  },
  "detected_at": "2026-04-11T20:44:34.663569+00:00",
  "num_detections": 2,
  "detections": [
    {
      "tag_id": 2,
      "tag_family": "tag36h11",
      "hamming": 0,
      "decision_margin": 60.87446975708008,
      "center": [
        1191.0917791489799,
        117.28347759646871
      ],
      "corners": [
        [
          1169.7218017578123,
          153.89234924316406
        ],
        [
          1214.5294189453125,
          165.1997375488281
        ],
        [
          1214.4407958984377,
          77.28431701660156
        ],
        [
          1167.8509521484375,
          69.76958465576175
        ]
      ],
      "homography": [
        [
          -6.039655248060174,
          24.35641282792426,
          1191.0917791489799
        ],
        [
          1.9001706943285457,
          45.31954919487315,
          117.28347759646871
        ],
        [
          -0.02423567850110732,
          0.020019327594666916,
          1.0
        ]
      ]
    },
    {
      "tag_id": 3,
      "tag_family": "tag36h11",
      "hamming": 0,
      "decision_margin": 58.88462829589844,
      "center": [
        1247.3494154173532,
        127.37706360454393
      ],
      "corners": [
        [
          1223.633056640625,
          167.22549438476562
        ],
        [
          1272.3975830078125,
          179.25195312500003
        ],
        [
          1271.0227050781248,
          87.60099792480467
        ],
        [
          1223.7949218749998,
          78.59558105468747
        ]
      ],
      "homography": [
        [
          5.386415510463396,
          -19.442017226342614,
          1247.3494154173532
        ],
        [
          3.3348021283001916,
          43.03125342679965,
          127.37706360454393
        ],
        [
          -0.01491176076066606,
          -0.015820590375919274,
          1.0
        ]
      ]
    }
  ],
  "ingest_metadata": {
    "original_name": "Hello AprilTag_frame_079260.png",
    "source": "Hello AprilTag.mp4",
    "dhash": "3838e0f0f0e6e198",
    "ingested_at": "2026-04-11T20:44:34.663597+00:00"
  }
}
