{
  "image_file": "745bbb4335f3_PC000002_MOV-0344_jpg_rf_1063881553d19b7148ae55c97da7764f.png",
  "image_sha256": "745bbb4335f3328516a16227b7e76c49f012e0b430b8be44b206d47dcf6cf199",
  "image_width": 640,
  "image_height": 360,
  "detector_config": {
    "library": "pupil-apriltags",
    "library_version": "1.0.4.post11",
    "family": "tag36h11",
    "nthreads": 4,
    "quad_decimate": 1.0,
    "quad_sigma": 0.0,
    "refine_edges": true,
    "decode_sharpening": 0.25
  },
  "detected_at": "2026-03-24T14:15:41.428502+00:00",
  "num_detections": 2,
  "detections": [
    {
      "tag_id": 19,
      "tag_family": "tag36h11",
      "hamming": 0,
      "decision_margin": 80.08467864990234,
      "center": [
        91.57174601150004,
        195.93004981348815
      ],
      "corners": [
        [
          50.34595870971679,
          226.24464416503906
        ],
        [
          122.97462463378908,
          231.01876831054688
        ],
        [
          130.0897979736328,
          167.60653686523438
        ],
        [
          59.82324218749998,
          160.45513916015622
        ]
      ],
      "homography": [
        [
          37.50560978770089,
          -5.429695551654073,
          91.57174601150004
        ],
        [
          6.860356351703697,
          29.49271939777583,
          195.93004981348815
        ],
        [
          0.019714190327770886,
          -0.014241226976493803,
          1.0
        ]
      ]
    },
    {
      "tag_id": 20,
      "tag_family": "tag36h11",
      "hamming": 0,
      "decision_margin": 79.54415893554688,
      "center": [
        236.19278733534887,
        207.97524926625184
      ],
      "corners": [
        [
          204.00242614746094,
          235.9371795654297
        ],
        [
          264.17562866210943,
          239.31697082519528
        ],
        [
          265.94351196289057,
          182.13249206542966
        ],
        [
          207.93373107910153,
          176.32415771484378
        ]
      ],
      "homography": [
        [
          34.75277115005039,
          -5.472511781244999,
          236.19278733534887
        ],
        [
          6.923920195737335,
          25.59313368772294,
          207.97524926625184
        ],
        [
          0.02214879896594934,
          -0.017237603907512222,
          1.0
        ]
      ]
    }
  ]
}
