{
  "image_file": "7ae73aa7565d_SF11_-_Southern_Maine_-_190_POV_frame_004366.png",
  "image_sha256": "7ae73aa7565d8310005918515440b9a6adf288a47363ddd34576deeb51f1cc14",
  "image_width": 1920,
  "image_height": 1080,
  "detector_config": {
    "library": "pupil-apriltags",
    "library_version": "1.0.4.post11",
    "family": "tag36h11",
    "nthreads": 4,
    "quad_decimate": 1.0,
    "quad_sigma": 0.0,
    "refine_edges": true,
    "decode_sharpening": 0.25
  },
  "detected_at": "2026-04-01T15:35:21.467739+00:00",
  "num_detections": 2,
  "detections": [
    {
      "tag_id": 4,
      "tag_family": "tag36h11",
      "hamming": 0,
      "decision_margin": 29.525114059448242,
      "center": [
        1631.0630112028243,
        448.1054166089982
      ],
      "corners": [
        [
          1615.302490234375,
          462.57397460937494
        ],
        [
          1637.4542236328123,
          463.20321655273443
        ],
        [
          1646.4407958984375,
          433.98822021484375
        ],
        [
          1624.324096679688,
          432.1862487792968
        ]
      ],
      "homography": [
        [
          42.68401876445546,
          7.069018195066752,
          1631.0630112028243
        ],
        [
          9.290582063521638,
          18.07341519296432,
          448.1054166089982
        ],
        [
          0.019386368514905758,
          0.007094875298635982,
          1.0
        ]
      ]
    },
    {
      "tag_id": 5,
      "tag_family": "tag36h11",
      "hamming": 0,
      "decision_margin": 49.179595947265625,
      "center": [
        838.2240168607767,
        437.64830947236806
      ],
      "corners": [
        [
          823.0846557617188,
          454.9981689453125
        ],
        [
          857.1217651367188,
          454.249237060547
        ],
        [
          853.6352539062501,
          419.9868774414063
        ],
        [
          819.1601562500001,
          420.9014587402343
        ]
      ],
      "homography": [
        [
          15.23145223114352,
          7.416887808948106,
          838.2240168607767
        ],
        [
          -1.4051748000757154,
          19.993805322293156,
          437.64830947236806
        ],
        [
          -0.002261702003616954,
          0.006637500071877853,
          1.0
        ]
      ]
    }
  ],
  "ingest_metadata": {
    "original_name": "SF11_-_Southern_Maine_-_190_POV_frame_004366.png",
    "source": "unknown",
    "dhash": "383a1380708594d6",
    "ingested_at": "2026-04-01T15:35:21.455301+00:00"
  }
}
