{
  "image_file": "7d9c561a15a6_TEAM_1229_ROBOT_REVEAL_2026__KWAZII_frame_004680.png",
  "image_sha256": "7d9c561a15a66c7920726466f1b30878f93fe9968c49fa543e9eb7c680a528f6",
  "image_width": 1920,
  "image_height": 1080,
  "detector_config": {
    "library": "pupil-apriltags",
    "library_version": "1.0.4.post11",
    "family": "tag36h11",
    "nthreads": 4,
    "quad_decimate": 1.0,
    "quad_sigma": 0.0,
    "refine_edges": true,
    "decode_sharpening": 0.25
  },
  "detected_at": "2026-04-01T04:48:18.702237+00:00",
  "num_detections": 3,
  "detections": [
    {
      "tag_id": 25,
      "tag_family": "tag36h11",
      "hamming": 0,
      "decision_margin": 55.304264068603516,
      "center": [
        1643.0047239838932,
        260.9762629273254
      ],
      "corners": [
        [
          1633.2457275390625,
          293.72210693359375
        ],
        [
          1656.9230957031248,
          283.3286437988282
        ],
        [
          1653.128662109375,
          227.0058746337891
        ],
        [
          1629.997314453125,
          240.08685302734372
        ]
      ],
      "homography": [
        [
          -31.17882781709818,
          -10.960386141990742,
          1643.0047239838932
        ],
        [
          -12.685130935372687,
          25.451840772375647,
          260.9762629273254
        ],
        [
          -0.026093429050172073,
          -0.007738911040743353,
          1.0
        ]
      ]
    },
    {
      "tag_id": 26,
      "tag_family": "tag36h11",
      "hamming": 0,
      "decision_margin": 79.41616821289062,
      "center": [
        1701.6031358981793,
        232.8808305404624
      ],
      "corners": [
        [
          1689.7246093750002,
          271.5447998046875
        ],
        [
          1719.9796142578123,
          258.0213012695312
        ],
        [
          1713.4090576171875,
          194.45318603515622
        ],
        [
          1685.5010986328127,
          210.85197448730472
        ]
      ],
      "homography": [
        [
          -39.01343673230007,
          -56.07182318348328,
          1701.6031358981793
        ],
        [
          -14.855972060363289,
          22.97557515155685,
          232.8808305404624
        ],
        [
          -0.03145070167387155,
          -0.03451620708183271,
          1.0
        ]
      ]
    },
    {
      "tag_id": 31,
      "tag_family": "tag36h11",
      "hamming": 0,
      "decision_margin": 60.305816650390625,
      "center": [
        269.0164297185122,
        425.64833065518997
      ],
      "corners": [
        [
          247.6636810302735,
          449.3537902832031
        ],
        [
          287.33544921875,
          450.91268920898443
        ],
        [
          289.68096923828125,
          402.7069091796875
        ],
        [
          250.2378540039063,
          399.75018310546875
        ]
      ],
      "homography": [
        [
          23.643871113322405,
          -1.7654081900809586,
          269.0164297185122
        ],
        [
          7.2523748780972115,
          23.597783166563033,
          425.64833065518997
        ],
        [
          0.014383476716597648,
          -0.0019957137980939413,
          1.0
        ]
      ]
    }
  ]
}
