{
  "image_file": "84093b187335_Q10_-_Southern_Maine_-_190_POV_frame_002596.png",
  "image_sha256": "84093b187335ca9158fbc67d2bbcafb2924cb86a89bef5c24d803aac459ed594",
  "image_width": 1280,
  "image_height": 720,
  "detector_config": {
    "library": "pupil-apriltags",
    "library_version": "1.0.4.post11",
    "family": "tag36h11",
    "nthreads": 4,
    "quad_decimate": 1.0,
    "quad_sigma": 0.0,
    "refine_edges": true,
    "decode_sharpening": 0.25
  },
  "detected_at": "2026-04-01T15:30:41.809845+00:00",
  "num_detections": 1,
  "detections": [
    {
      "tag_id": 3,
      "tag_family": "tag36h11",
      "hamming": 0,
      "decision_margin": 28.240692138671875,
      "center": [
        1038.5772007940948,
        424.6490724102116
      ],
      "corners": [
        [
          1034.4337158203125,
          434.8916931152343
        ],
        [
          1047.3885498046875,
          431.27838134765636
        ],
        [
          1042.8784179687502,
          414.0165405273438
        ],
        [
          1029.9334716796877,
          418.1458740234374
        ]
      ],
      "homography": [
        [
          -8.212284838558162,
          6.965634754164511,
          1038.5772007940948
        ],
        [
          -7.938930386710298,
          10.42670314821464,
          424.6490724102116
        ],
        [
          -0.014140586703661046,
          0.0045376565428702905,
          1.0
        ]
      ]
    }
  ],
  "ingest_metadata": {
    "original_name": "Q10_-_Southern_Maine_-_190_POV_frame_002596.png",
    "source": "unknown",
    "dhash": "526a48d9d4ccc4f8",
    "ingested_at": "2026-04-01T15:30:41.805296+00:00"
  }
}
