{
  "image_file": "ca7b314a23c3_FRC_Team_1306_BadgerBOTS_Presents__Gimli__-_2026_Rebuilt_Rob.png",
  "image_sha256": "ca7b314a23c384a4d79ad9b8ac664114421ff8cb73cada3ed9b4ded86d165e87",
  "image_width": 1920,
  "image_height": 1080,
  "detector_config": {
    "library": "pupil-apriltags",
    "library_version": "1.0.4.post11",
    "family": "tag36h11",
    "nthreads": 4,
    "quad_decimate": 1.0,
    "quad_sigma": 0.0,
    "refine_edges": true,
    "decode_sharpening": 0.25
  },
  "detected_at": "2026-04-01T04:29:32.248030+00:00",
  "num_detections": 2,
  "detections": [
    {
      "tag_id": 25,
      "tag_family": "tag36h11",
      "hamming": 0,
      "decision_margin": 79.16324615478516,
      "center": [
        632.8418886846861,
        605.5106553885753
      ],
      "corners": [
        [
          606.1165161132815,
          625.9807739257814
        ],
        [
          653.1262207031249,
          635.3956909179688
        ],
        [
          658.8701782226561,
          585.574462890625
        ],
        [
          612.3086547851564,
          575.2589111328125
        ]
      ],
      "homography": [
        [
          29.50079471325887,
          -5.233757179025584,
          632.8418886846861
        ],
        [
          10.780583743868302,
          22.979038110059264,
          605.5106553885753
        ],
        [
          0.009655918898724766,
          -0.003558007975003431,
          1.0
        ]
      ]
    },
    {
      "tag_id": 26,
      "tag_family": "tag36h11",
      "hamming": 0,
      "decision_margin": 77.86064147949219,
      "center": [
        734.0250302834152,
        623.2204264577391
      ],
      "corners": [
        [
          710.60498046875,
          644.1279907226564
        ],
        [
          753.8624877929688,
          650.999938964844
        ],
        [
          756.7105102539062,
          602.9686279296874
        ],
        [
          713.9025268554688,
          595.0417480468748
        ]
      ],
      "homography": [
        [
          29.97831962618079,
          -4.763343717374024,
          734.0250302834152
        ],
        [
          10.889098354558653,
          21.53418434456762,
          623.2204264577391
        ],
        [
          0.011532823517618772,
          -0.0043995353034823005,
          1.0
        ]
      ]
    }
  ]
}
