{
  "image_file": "d182e040b457_FRC_2026_1388_1080p_Robot_Reveal_frame_002580.png",
  "image_sha256": "d182e040b457b54d2401ad72c43a95fe96fa97c3b6b8dec73d06f486095cf8d0",
  "image_width": 1920,
  "image_height": 1080,
  "detector_config": {
    "library": "pupil-apriltags",
    "library_version": "1.0.4.post11",
    "family": "tag36h11",
    "nthreads": 4,
    "quad_decimate": 1.0,
    "quad_sigma": 0.0,
    "refine_edges": true,
    "decode_sharpening": 0.25
  },
  "detected_at": "2026-04-01T04:52:33.513740+00:00",
  "num_detections": 2,
  "detections": [
    {
      "tag_id": 5,
      "tag_family": "tag36h11",
      "hamming": 0,
      "decision_margin": 22.149667739868164,
      "center": [
        1670.8789433634956,
        235.04177323942218
      ],
      "corners": [
        [
          1635.4609374999998,
          266.2135009765625
        ],
        [
          1704.026123046875,
          260.2015380859375
        ],
        [
          1708.4158935546875,
          202.00514221191406
        ],
        [
          1638.6547851562495,
          210.5826110839843
        ]
      ],
      "homography": [
        [
          -1.498165961320184,
          10.585065432957435,
          1670.8789433634956
        ],
        [
          -8.708987395654393,
          30.194793355506732,
          235.04177323942218
        ],
        [
          -0.021582111290960007,
          0.007462444998097464,
          1.0
        ]
      ]
    },
    {
      "tag_id": 8,
      "tag_family": "tag36h11",
      "hamming": 0,
      "decision_margin": 20.518037796020508,
      "center": [
        1831.8429299907277,
        218.35804363510465
      ],
      "corners": [
        [
          1790.453979492187,
          251.97605895996094
        ],
        [
          1869.195068359375,
          245.63485717773432
        ],
        [
          1875.6260986328127,
          182.79533386230466
        ],
        [
          1795.5429687499998,
          191.849594116211
        ]
      ],
      "homography": [
        [
          0.8539521373336344,
          9.795291012054577,
          1831.8429299907277
        ],
        [
          -8.466710415760136,
          32.23444030818962,
          218.35804363510465
        ],
        [
          -0.021198061550879804,
          0.006912289203589893,
          1.0
        ]
      ]
    }
  ],
  "ingest_metadata": {
    "original_name": "FRC_2026_1388_1080p_Robot_Reveal_frame_002580.png",
    "source": "unknown",
    "dhash": "46f4dcf9eaf0f9f8",
    "ingested_at": "2026-04-01T04:52:33.505301+00:00"
  }
}
