{
  "image_file": "e3a09178410d_FRC_ROBOT_POV_-_Southern_Cross_2024_frame_014637.png",
  "image_sha256": "e3a09178410df22666e9120ac1ca49dad8f1d9d198abc73b2ee811045a77225b",
  "image_width": 1920,
  "image_height": 1080,
  "detector_config": {
    "library": "pupil-apriltags",
    "library_version": "1.0.4.post11",
    "family": "tag36h11",
    "nthreads": 4,
    "quad_decimate": 1.0,
    "quad_sigma": 0.0,
    "refine_edges": true,
    "decode_sharpening": 0.25
  },
  "detected_at": "2026-04-01T16:14:58.823762+00:00",
  "num_detections": 2,
  "detections": [
    {
      "tag_id": 7,
      "tag_family": "tag36h11",
      "hamming": 0,
      "decision_margin": 24.400089263916016,
      "center": [
        1077.0307117673228,
        545.2216199420183
      ],
      "corners": [
        [
          1037.5007324218748,
          587.6180419921875
        ],
        [
          1120.71337890625,
          577.2420043945312
        ],
        [
          1116.3598632812502,
          503.04058837890614
        ],
        [
          1034.4958496093748,
          514.0426025390624
        ]
      ],
      "homography": [
        [
          35.467436726537244,
          -6.7047099877729535,
          1077.0307117673228
        ],
        [
          -8.282166807012008,
          32.61778862160395,
          545.2216199420183
        ],
        [
          -0.0053831151116045806,
          -0.007929780657270737,
          1.0
        ]
      ]
    },
    {
      "tag_id": 8,
      "tag_family": "tag36h11",
      "hamming": 0,
      "decision_margin": 49.7542724609375,
      "center": [
        813.2929305015424,
        580.2334147646704
      ],
      "corners": [
        [
          775.8514404296876,
          619.98388671875
        ],
        [
          846.8016967773438,
          611.0838012695311
        ],
        [
          850.9306640624999,
          540.2745971679688
        ],
        [
          781.97509765625,
          551.4001464843751
        ]
      ],
      "homography": [
        [
          20.15155490384723,
          -15.26200005722478,
          813.2929305015424
        ],
        [
          -15.586652616476048,
          25.784344900203788,
          580.2334147646704
        ],
        [
          -0.01820532349777425,
          -0.015591504659389849,
          1.0
        ]
      ]
    }
  ],
  "ingest_metadata": {
    "original_name": "FRC_ROBOT_POV_-_Southern_Cross_2024_frame_014637.png",
    "source": "unknown",
    "dhash": "ce587287470adbb9",
    "ingested_at": "2026-04-01T16:14:58.815300+00:00"
  }
}
