{
  "image_file": "f9af6434551f_frame000661_5_png_rf_c1a63a86a925ca66abd01371f4850b4c.png",
  "image_sha256": "f9af6434551ff73a556fc996f6d0b2814b237f15aa60d33c57bfc0635707da2d",
  "image_width": 640,
  "image_height": 640,
  "detector_config": {
    "library": "pupil-apriltags",
    "library_version": "1.0.4.post11",
    "family": "tag36h11",
    "nthreads": 4,
    "quad_decimate": 1.0,
    "quad_sigma": 0.0,
    "refine_edges": true,
    "decode_sharpening": 0.25
  },
  "detected_at": "2026-03-24T14:17:04.451177+00:00",
  "num_detections": 1,
  "detections": [
    {
      "tag_id": 0,
      "tag_family": "tag36h11",
      "hamming": 0,
      "decision_margin": 79.67464447021484,
      "center": [
        411.531987624799,
        216.89020759880393
      ],
      "corners": [
        [
          381.9261169433593,
          212.68601989746094
        ],
        [
          414.0359191894531,
          241.89906311035153
        ],
        [
          440.4530334472656,
          220.9971466064453
        ],
        [
          409.3158874511719,
          194.75616455078128
        ]
      ],
      "homography": [
        [
          5.665240185698229,
          -28.40955718447958,
          411.531987624799
        ],
        [
          8.475242492309008,
          1.782410552001325,
          216.89020759880393
        ],
        [
          -0.024639896395410442,
          -0.0363409204691343,
          1.0
        ]
      ]
    }
  ],
  "ingest_metadata": {
    "original_name": "frame000661_5_png_rf_c1a63a86a925ca66abd01371f4850b4c.png",
    "source": "unknown",
    "dhash": "80a0882885cce8b4",
    "ingested_at": "2026-03-24T14:17:04.443712+00:00"
  }
}
